pgldapsync/__init__.py
pgldapsync/config.ini.example
pgldapsync/config_default.ini
pgldapsync/ldaputils/__init__.py
pgldapsync/ldaputils/connection.py
pgldapsync/ldaputils/users.py
pgldapsync/pgutils/__init__.py
pgldapsync/pgutils/connection.py
pgldapsync/pgutils/roles.py
pgldapsync-1.0.0.dist-info/LICENSE
pgldapsync-1.0.0.dist-info/METADATA
pgldapsync-1.0.0.dist-info/WHEEL
pgldapsync-1.0.0.dist-info/entry_points.txt
pgldapsync-1.0.0.dist-info/top_level.txt
pgldapsync-1.0.0.dist-info/RECORD
