Metadata-Version: 2.1
Name: pgldapsync
Version: 1.0.0
Summary: Synchronise LDAP users to Postgres
Home-page: https://github.com/enterprisedb/pgldapsync
Author: Dave Page
Author-email: dave.page@enterprisedb.com
License: PostgreSQL
Platform: UNKNOWN
Classifier: Programming Language :: Python :: 3
Classifier: Programming Language :: Python :: 2.7
Classifier: License :: OSI Approved :: PostgreSQL License
Classifier: Operating System :: OS Independent
License-File: LICENSE
Requires-Dist: ldap3 (>=2.5.1)
Requires-Dist: psycopg2-binary (>=2.7.5)
Requires-Dist: pyasn1 (>=0.4.4)
